experimental/__init__.py
experimental/algorithms/__init__.py
experimental/algorithms/example_algorithm/__init__.py
experimental/algorithms/example_algorithm/example_algorithm.py
experimental/algorithms/example_algorithm/metadata.json
mosaicml_experimental-0.0.2.dist-info/LICENSE
mosaicml_experimental-0.0.2.dist-info/METADATA
mosaicml_experimental-0.0.2.dist-info/WHEEL
mosaicml_experimental-0.0.2.dist-info/top_level.txt
mosaicml_experimental-0.0.2.dist-info/RECORD
